odoo/addons/hr_experience/README.rst
odoo/addons/hr_experience/__init__.py
odoo/addons/hr_experience/__manifest__.py
odoo/addons/hr_experience/i18n/ar.po
odoo/addons/hr_experience/i18n/cs_CZ.po
odoo/addons/hr_experience/i18n/de.po
odoo/addons/hr_experience/i18n/es.po
odoo/addons/hr_experience/i18n/fa.po
odoo/addons/hr_experience/i18n/fi.po
odoo/addons/hr_experience/i18n/fr.po
odoo/addons/hr_experience/i18n/gl.po
odoo/addons/hr_experience/i18n/hr.po
odoo/addons/hr_experience/i18n/hr_HR.po
odoo/addons/hr_experience/i18n/hr_experience.pot
odoo/addons/hr_experience/i18n/it.po
odoo/addons/hr_experience/i18n/lt.po
odoo/addons/hr_experience/i18n/nl_NL.po
odoo/addons/hr_experience/i18n/pl.po
odoo/addons/hr_experience/i18n/pt_BR.po
odoo/addons/hr_experience/i18n/ro.po
odoo/addons/hr_experience/i18n/sl.po
odoo/addons/hr_experience/models/__init__.py
odoo/addons/hr_experience/models/hr_academic.py
odoo/addons/hr_experience/models/hr_certification.py
odoo/addons/hr_experience/models/hr_curriculum.py
odoo/addons/hr_experience/models/hr_employee.py
odoo/addons/hr_experience/models/hr_experience.py
odoo/addons/hr_experience/security/hr_security.xml
odoo/addons/hr_experience/security/ir.model.access.csv
odoo/addons/hr_experience/static/description/icon.png
odoo/addons/hr_experience/views/hr_academic_view.xml
odoo/addons/hr_experience/views/hr_certification_view.xml
odoo/addons/hr_experience/views/hr_employee_view.xml
odoo/addons/hr_experience/views/hr_professional_view.xml
odoo11_addon_hr_experience-11.0.1.0.1.99.dev10.dist-info/METADATA
odoo11_addon_hr_experience-11.0.1.0.1.99.dev10.dist-info/WHEEL
odoo11_addon_hr_experience-11.0.1.0.1.99.dev10.dist-info/top_level.txt
odoo11_addon_hr_experience-11.0.1.0.1.99.dev10.dist-info/RECORD
